Workbook

Sheet Léeme
B2: COST TO SERVE — BEBIDAS · Modelo Excel
B4: Cómo usarlo:
B5: 1. Hoja 'Inputs': llena las celdas amarillas (texto azul) con tus supuestos generales. Traen el caso demo precargado.
B6: 2. Hoja 'Canales': ajusta mix, drop size, descuento, DSO y merma de cada canal.
B7: 3. Hoja 'Modelo': P&L por canal 100% en fórmulas — no editar (texto negro).
B8: 4. Hojas 'Waterfall' y 'Gráficos': se actualizan solos al cambiar cualquier input.
B10: Fórmulas del modelo (metodología Activity-Based Costing):
B11: · Almacenaje = (costo posición/mes ÷ cajas/pallet) × (DIO ÷ 30)
B12: · Manipulación = costo base × factor drop size (1,8 si <10 cajas; 1,2 si <30; 0,7 pallet completo)
B13: · Dist. secundaria = costo camión/día ÷ (entregas/día × drop size); ×0,55 si drop ≥100 (entrega dedicada)
B14: · Comercial = (costo vendedor/día ÷ visitas/día) × intensidad ÷ drop size; e-commerce usa fee % de la venta
B15: · Financiero = precio neto × WACC × (DIO + DSO) ÷ 365
... B20: Fuente supuestos demo: estimaciones propias industria bebidas Chile 2026 (misma base que cost_to_serve.html).

Sheet Inputs
B2: COST TO SERVE — BEBIDAS · Supuestos generales
B3: Llena SOLO las celdas amarillas (texto azul). Todo lo demás se calcula solo. Valores precargados = caso demo embotelladora chilena.
B5: Producto y precio
B6: Precio venta lista por caja | C6: 9500 | D6: CLP | E6: Precio de lista antes de descuentos. Caja estándar = 24 unidades / ~12 L.
B7: Litros por caja | C7: 12 | D7: L | E7: Para expresar el CTS también en $/litro.
B8: Costo de producción (COGS) por caja | C8: 4200 | D8: CLP | E8: Insumos + envase + MO + energía. Típico bebidas: 40–50% del precio.
B9: Volumen mensual | C9: 400000 | D9: cajas | E9: Escala del negocio; referencia informativa.
B10: Logística
B11: Costo bodega por posición pallet / mes | C11: 12000 | D11: CLP | E11: Arriendo + energía + personal ÷ posiciones. Chile: 8.000–15.000.
B12: Cajas por pallet | C12: 60 | D12: cajas | E12: Bebidas: 50–70 según formato.
B13: Días de inventario (DIO) | C13: 25 | D13: días | E13: Días promedio en bodega. Impacta almacenaje y costo financiero.
B14: Costo manipulación por caja (base) | C14: 150 | D14: CLP | E14: Recepción + picking + carga. Se ajusta por drop size del canal.
B15: Transporte primario por caja | C15: 250 | D15: CLP | E15: Planta → CD en camión completo. 0 si vendes desde planta.
B16: Costo camión de reparto por día | C16: 220000 | D16: CLP | E16: Chofer + peoneta + combustible + depreciación. Chile: 180.000–280.000.
B17: Entregas por camión por día | C17: 25 | D17: paradas | E17: Tradicional: 25–40; supermercados: 5–10.
B18: Comercial y financiero
B19: Costo total vendedor / mes | C19: 1600000 | D19: CLP | E19: Sueldo + comisiones + vehículo + tecnología. Chile: 1,4–2,0 MM.
B20: Días hábiles por mes | C20: 21 | D20: días | E20: Para llevar el costo del vendedor a costo por día.
B21: Visitas por vendedor por día | C21: 30 | D21: visitas | E21: Preventa tradicional: 25–40. Cuentas clave: 3–6.
B22: Costo de capital anual (WACC) | C22: 0.12 | D22: % | E22: Tasa para valorizar capital de trabajo (inventario + cuentas por cobrar).
B23: Merma base sobre venta | C23: 0.01 | D23: % | E23: Vencimiento + rotura + robo. Bebidas: 0,5–2%. Cada canal suma ajuste propio.
B24: Overhead logístico-comercial sobre venta | C24: 0.03 | D24: % | E24: Planificación, TI, back-office supply chain y order-to-cash.
B25: Fee plataforma e-commerce sobre venta | C25: 0.02 | D25: % | E25: Comisión marketplace / pasarela; reemplaza al vendedor en canal e-commerce.
B27: Leyenda: fondo amarillo + texto azul = input editable · texto negro = fórmula · verde = trae dato de otra hoja.

Sheet Canales
B2: Canales de venta
B3: Aquí vive la diferencia real del CTS. Llena las celdas amarillas por canal; el mix se normaliza solo en la hoja Modelo.
B5: Canal | C5: Mix % | D5: Drop size (cajas/entrega) | E5: Pedidos / mes | F5: Descuento % | G5: DSO (días) | H5: Merma adic. % | I5: Intensidad visita (0–1) | J5: Comentario
B6: Supermercados | C6: 0.35 | D6: 120 | E6: 8 | F6: 0.18 | G6: 60 | H6: 0.003 | I6: 0.15 | J6: Pallets completos, pocas entregas; descuentos altos y pagan a 60 días.
B7: Mayoristas | C7: 0.2 | D7: 200 | E7: 4 | F7: 0.14 | G7: 30 | H7: 0.002 | I7: 0.1 | J7: Drop size gigante, muy barato de servir; margen unitario bajo.
B8: Tradicional (almacenes) | C8: 0.3 | D8: 8 | E8: 4 | F8: 0.05 | G8: 0 | H8: 0.01 | I8: 1 | J8: Pedidos chicos, muchas visitas: CTS más alto, pero paga contado.
B9: HoReCa (bares/restaurantes) | C9: 0.1 | D9: 15 | E9: 4 | F9: 0.08 | G9: 30 | H9: 0.015 | I9: 0.8 | J9: Ventana horaria, retornable, crédito 30 días.
B10: E-commerce / D2C | C10: 0.05 | D10: 2 | E10: 30 | F10: 0 | G10: 0 | H10: 0.02 | I10: 0 | J10: Sin vendedor (intensidad 0 → usa fee plataforma); picking unitario carísimo.
B12: Intensidad de visita: 1 = preventa completa (tradicional); 0,15 = key account con pocas visitas; 0 = sin fuerza de venta (e-commerce).

Sheet Modelo
B2: Motor de cálculo — CTS por canal (CLP/caja)
B3: Todo son fórmulas: cambia Inputs o Canales y este P&L se recalcula. Fórmulas idénticas al modelo web (ABC).
B5: Canal | C5: Mix normalizado | D5: Precio neto | E5: Almacenaje | F5: Manipulación | G5: Transp. primario | H5: Dist. secundaria | I5: Comercial | J5: Financiero | K5: Mermas | L5: Overhead | M5: CTS total | N5: CTS % venta | O5: Margen / caja | P5: Margen % | Q5: CTS / litro
B6: =Canales!B6 | C6: =Canales!$C$6/SUM(Canales!$C$6:$C$10) | D6: =Inputs!$C$6*(1-Canales!$F$6) | E6: =(Inputs!$C$11/Inputs!$C$12)*(Inputs!$C$13/30) | F6: =Inputs!$C$14*IF(Canales!$D$6<10,1.8,IF(Canales!$D$6<30,1.2,0.7)) | G6: =Inputs!$C$15 | H6: =Inputs!$C$16/(Inputs!$C$17*Canales!$D$6)*IF(Canales!$D$6>=100,0.55,1) | I6: =IF(Canales!$I$6>0,((Inputs!$C$19/Inputs!$C$20)/Inputs!$C$21)*Canales!$I$6/Canales!$D$6,D6*Inputs!$C$25) | J6: =D6*Inputs!$C$22*(Inputs!$C$13+Canales!$G$6)/365 | K6: =D6*(Inputs!$C$23+Canales!$H$6) | L6: =D6*Inputs!$C$24 | M6: =SUM(E6:L6) | N6: =M6/D6 | O6: =D6-Inputs!$C$8-M6 | P6: =O6/D6 | Q6: =M6/Inputs!$C$7
B7: =Canales!B7 | C7: =Canales!$C$7/SUM(Canales!$C$6:$C$10) | D7: =Inputs!$C$6*(1-Canales!$F$7) | E7: =(Inputs!$C$11/Inputs!$C$12)*(Inputs!$C$13/30) | F7: =Inputs!$C$14*IF(Canales!$D$7<10,1.8,IF(Canales!$D$7<30,1.2,0.7)) | G7: =Inputs!$C$15 | H7: =Inputs!$C$16/(Inputs!$C$17*Canales!$D$7)*IF(Canales!$D$7>=100,0.55,1) | I7: =IF(Canales!$I$7>0,((Inputs!$C$19/Inputs!$C$20)/Inputs!$C$21)*Canales!$I$7/Canales!$D$7,D7*Inputs!$C$25) | J7: =D7*Inputs!$C$22*(Inputs!$C$13+Canales!$G$7)/365 | K7: =D7*(Inputs!$C$23+Canales!$H$7) | L7: =D7*Inputs!$C$24 | M7: =SUM(E7:L7) | N7: =M7/D7 | O7: =D7-Inputs!$C$8-M7 | P7: =O7/D7 | Q7: =M7/Inputs!$C$7
B8: =Canales!B8 | C8: =Canales!$C$8/SUM(Canales!$C$6:$C$10) | D8: =Inputs!$C$6*(1-Canales!$F$8) | E8: =(Inputs!$C$11/Inputs!$C$12)*(Inputs!$C$13/30) | F8: =Inputs!$C$14*IF(Canales!$D$8<10,1.8,IF(Canales!$D$8<30,1.2,0.7)) | G8: =Inputs!$C$15 | H8: =Inputs!$C$16/(Inputs!$C$17*Canales!$D$8)*IF(Canales!$D$8>=100,0.55,1) | I8: =IF(Canales!$I$8>0,((Inputs!$C$19/Inputs!$C$20)/Inputs!$C$21)*Canales!$I$8/Canales!$D$8,D8*Inputs!$C$25) | J8: =D8*Inputs!$C$22*(Inputs!$C$13+Canales!$G$8)/365 | K8: =D8*(Inputs!$C$23+Canales!$H$8) | L8: =D8*Inputs!$C$24 | M8: =SUM(E8:L8) | N8: =M8/D8 | O8: =D8-Inputs!$C$8-M8 | P8: =O8/D8 | Q8: =M8/Inputs!$C$7
B9: =Canales!B9 | C9: =Canales!$C$9/SUM(Canales!$C$6:$C$10) | D9: =Inputs!$C$6*(1-Canales!$F$9) | E9: =(Inputs!$C$11/Inputs!$C$12)*(Inputs!$C$13/30) | F9: =Inputs!$C$14*IF(Canales!$D$9<10,1.8,IF(Canales!$D$9<30,1.2,0.7)) | G9: =Inputs!$C$15 | H9: =Inputs!$C$16/(Inputs!$C$17*Canales!$D$9)*IF(Canales!$D$9>=100,0.55,1) | I9: =IF(Canales!$I$9>0,((Inputs!$C$19/Inputs!$C$20)/Inputs!$C$21)*Canales!$I$9/Canales!$D$9,D9*Inputs!$C$25) | J9: =D9*Inputs!$C$22*(Inputs!$C$13+Canales!$G$9)/365 | K9: =D9*(Inputs!$C$23+Canales!$H$9) | L9: =D9*Inputs!$C$24 | M9: =SUM(E9:L9) | N9: =M9/D9 | O9: =D9-Inputs!$C$8-M9 | P9: =O9/D9 | Q9: =M9/Inputs!$C$7
B10: =Canales!B10 | C10: =Canales!$C$10/SUM(Canales!$C$6:$C$10) | D10: =Inputs!$C$6*(1-Canales!$F$10) | E10: =(Inputs!$C$11/Inputs!$C$12)*(Inputs!$C$13/30) | F10: =Inputs!$C$14*IF(Canales!$D$10<10,1.8,IF(Canales!$D$10<30,1.2,0.7)) | G10: =Inputs!$C$15 | H10: =Inputs!$C$16/(Inputs!$C$17*Canales!$D$10)*IF(Canales!$D$10>=100,0.55,1) | I10: =IF(Canales!$I$10>0,((Inputs!$C$19/Inputs!$C$20)/Inputs!$C$21)*Canales!$I$10/Canales!$D$10,D10*Inputs!$C$25) | J10: =D10*Inputs!$C$22*(Inputs!$C$13+Canales!$G$10)/365 | K10: =D10*(Inputs!$C$23+Canales!$H$10) | L10: =D10*Inputs!$C$24 | M10: =SUM(E10:L10) | N10: =M10/D10 | O10: =D10-Inputs!$C$8-M10 | P10: =O10/D10 | Q10: =M10/Inputs!$C$7
B11: Promedio ponderado | C11: =SUM(C6:C10) | D11: =SUMPRODUCT($C$6:$C$10,D6:D10) | E11: =SUMPRODUCT($C$6:$C$10,E6:E10) | F11: =SUMPRODUCT($C$6:$C$10,F6:F10) | G11: =SUMPRODUCT($C$6:$C$10,G6:G10) | H11: =SUMPRODUCT($C$6:$C$10,H6:H10) | I11: =SUMPRODUCT($C$6:$C$10,I6:I10) | J11: =SUMPRODUCT($C$6:$C$10,J6:J10) | K11: =SUMPRODUCT($C$6:$C$10,K6:K10) | ... Q11: =SUMPRODUCT($C$6:$C$10,Q6:Q10)

Sheet Waterfall
B2: Waterfall: precio lista → margen neto (promedio ponderado)
B3: Tabla auxiliar para el gráfico. Base = columna invisible; Valor = tramo visible.
B5: Concepto | C5: Base | D5: Valor
B6: Precio lista | C6: 0 | D6: =Inputs!$C$6
B7: Descuentos | C7: =C6 | D7: =Inputs!$C$6-Modelo!D11
B8: COGS | C8: =C7-D8 | D8: =Inputs!$C$8
B9: Almacenaje | C9: =C8-D9 | D9: =Modelo!E11
B10: Manipulación | C10: =C9-D10 | D10: =Modelo!F11
B11: Transp. primario | C11: =C10-D11 | D11: =Modelo!G11
B12: Dist. secundaria | C12: =C11-D12 | D12: =Modelo!H11
B13: Comercial | C13: =C12-D13 | D13: =Modelo!I11
B14: Financiero | C14: =C13-D14 | D14: =Modelo!J11
B15: Mermas | C15: =C14-D15 | D15: =Modelo!K11
B16: Overhead | C16: =C15-D16 | D16: =Modelo!L11
B17: Margen neto | C17: 0 | D17: =Modelo!O11

Sheet Gráficos
B2: Gráficos por canal (se actualizan solos)
